<root>
	<PMID Version="1">24092016</PMID>
	<Summary>
		1: Nenasheva VV, Kovaleva GV, Khaidarova NV, Novosadova EV, Manuilova ES, AntonovSA, Tarantul VZ. Trim14 overexpression causes the same transcriptional changes inmouse embryonic stem cells and human HEK293 cells. In Vitro Cell Dev Biol Anim.2014 Feb;50(2):121-8. doi: 10.1007/s11626-013-9683-4. Epub 2013 Oct 3. PubMedPMID: 24092016.
	</Summary>
	<MeshHeadingList>
	    <MeshHeading>
			<DescriptorName MajorTopicYN="N" UI="D000818">Animals</DescriptorName>
	    </MeshHeading>
	    <MeshHeading>
			<DescriptorName MajorTopicYN="N" UI="D002454">Cell Differentiation</DescriptorName>
			<QualifierName MajorTopicYN="Y" UI="Q000235">genetics</QualifierName>
	    </MeshHeading>
	    <MeshHeading>
			<DescriptorName MajorTopicYN="N" UI="D058732">Embryoid Bodies</DescriptorName>
	    </MeshHeading>
	    <MeshHeading>
			<DescriptorName MajorTopicYN="N" UI="D053595">Embryonic Stem Cells</DescriptorName>
			<QualifierName MajorTopicYN="Y" UI="Q000378">metabolism</QualifierName>
	    </MeshHeading>
	    <MeshHeading>
			<DescriptorName MajorTopicYN="N" UI="D018507">Gene Expression Regulation, Developmental</DescriptorName>
	    </MeshHeading>
	    <MeshHeading>
			<DescriptorName MajorTopicYN="N" UI="D057809">HEK293 Cells</DescriptorName>
	    </MeshHeading>
	    <MeshHeading>
			<DescriptorName MajorTopicYN="N" UI="D006801">Humans</DescriptorName>
	    </MeshHeading>
	    <MeshHeading>
			<DescriptorName MajorTopicYN="N" UI="D051379">Mice</DescriptorName>
	    </MeshHeading>
	    <MeshHeading>
			<DescriptorName MajorTopicYN="N" UI="D032383">Myocytes, Cardiac</DescriptorName>
			<QualifierName MajorTopicYN="N" UI="Q000378">metabolism</QualifierName>
	    </MeshHeading>
	    <MeshHeading>
			<DescriptorName MajorTopicYN="N" UI="D015534">Trans-Activators</DescriptorName>
			<QualifierName MajorTopicYN="Y" UI="Q000096">biosynthesis</QualifierName>
			<QualifierName MajorTopicYN="N" UI="Q000235">genetics</QualifierName>
	    </MeshHeading>
	    <MeshHeading>
			<DescriptorName MajorTopicYN="Y" UI="D014158">Transcription, Genetic</DescriptorName>
	    </MeshHeading>
	</MeshHeadingList>
</root>
